randomchessgame/__init__.py
randomchessgame/randomchessgame.py
randomchessgame-4.0.8.dist-info/LICENSE
randomchessgame-4.0.8.dist-info/METADATA
randomchessgame-4.0.8.dist-info/WHEEL
randomchessgame-4.0.8.dist-info/top_level.txt
randomchessgame-4.0.8.dist-info/RECORD
