Metadata-Version: 2.1
Name: randomchessgame
Version: 4.0.8
Summary: Python library to come in handy when random chess game is neeed.
Home-page: https://github.com/lot022/randomcg
Author: lot022
License: MIT
Keywords: chess
Classifier: Programming Language :: Python
Classifier: Operating System :: Unix
Classifier: License :: OSI Approved :: MIT License
Classifier: Topic :: Games/Entertainment :: Board Games
Classifier: Topic :: Software Development :: Libraries :: Python Modules
Classifier: Programming Language :: Python :: 3.7
Classifier: Programming Language :: Python :: 3.8
Classifier: Programming Language :: Python :: 3.9
Classifier: Programming Language :: Python :: 3.10
Requires-Python: >=3.7
License-File: LICENSE
